stack_upgrade_analyzer/__init__.py
stack_upgrade_analyzer/cli.py
stack_upgrade_analyzer/upgrade_analyzer.py
stack_upgrade_analyzer/utils.py
stack_upgrade_analyzer/data/changes/node/10.0_11.0_changes.md
stack_upgrade_analyzer/data/changes/node/11.0_12.0_changes.md
stack_upgrade_analyzer/data/changes/node/12.0_13.0_changes.md
stack_upgrade_analyzer/data/changes/node/13.0_14.0_changes.md
stack_upgrade_analyzer/data/changes/node/14.0_15.0_changes.md
stack_upgrade_analyzer/data/changes/node/15.0_16.0_changes.md
stack_upgrade_analyzer/data/changes/node/16.0_17.0_changes.md
stack_upgrade_analyzer/data/changes/node/17.0_18.0_changes.md
stack_upgrade_analyzer/data/changes/node/18.0_19.0_changes.md
stack_upgrade_analyzer/data/changes/node/19.0_20.0_changes.md
stack_upgrade_analyzer/data/changes/node/20.0_21.0_changes.md
stack_upgrade_analyzer/data/changes/node/21.0_22.0_changes.md
stack_upgrade_analyzer/data/changes/node/7.10_8.0_changes.md
stack_upgrade_analyzer/data/changes/node/8.0_9.0_changes.md
stack_upgrade_analyzer/data/changes/node/9.0_10.0_changes.md
stack_upgrade_analyzer-1.1.12.dist-info/licenses/LICENSE
stack_upgrade_analyzer-1.1.12.dist-info/METADATA
stack_upgrade_analyzer-1.1.12.dist-info/WHEEL
stack_upgrade_analyzer-1.1.12.dist-info/entry_points.txt
stack_upgrade_analyzer-1.1.12.dist-info/top_level.txt
stack_upgrade_analyzer-1.1.12.dist-info/RECORD
