Metadata-Version: 2.4
Name: stack-upgrade-analyzer
Version: 1.1.12
Summary: A tool for analyzing code compatibility issues when upgrading technology stacks
Home-page: https://github.com/trilogy-group/upgrade-analyzer
Author: Trilogy Group
Author-email: info@trilogy.com
License: MIT
Classifier: Programming Language :: Python :: 3
Classifier: License :: OSI Approved :: MIT License
Classifier: Operating System :: OS Independent
Requires-Python: >=3.7
License-File: LICENSE
Requires-Dist: click
Requires-Dist: boto3
Requires-Dist: requests
Requires-Dist: python-dotenv
Dynamic: author
Dynamic: author-email
Dynamic: classifier
Dynamic: description
Dynamic: description-content-type
Dynamic: home-page
Dynamic: license-file
Dynamic: requires-dist
Dynamic: requires-python
Dynamic: summary
